[
  {
    "id": 1680,
    "channel_id": "advokatgrikevich",
    "date": "2026-07-14T04:04:01+00:00",
    "text": "**Юрист, который берётся за любое ваше дело, зарабатывает на ваших проигрышах.**\n\nМы так не работаем. Мы отказываем. Регулярно. И это лучшее, что мы можем для вас сделать.\n\nПеред тем как подписать договор с любым юристом, задайте один вопрос: «От каких дел вы отказываетесь?» Если в ответ слышите «берёмся за всё», разворачивайтесь и уходите. Вам только что пообещали взять деньги за заведомый проигрыш.\n\nРассказываю, когда «нет» говорим мы. И почему это ваша страховка.\n\n**Отказ первый: **срок исковой давности мёртв. Прошло три года, и долг юридически труп. Реанимировать нечем. Мы видели это с обеих сторон: в одном деле мы защитили клиента от взыскания 2,5 миллиона займа именно потому, что кредитор спохватился поздно. Брать с вас деньги за «взыскание» просроченного долга, это не юридическая услуга, а отъём средств. Кто-то берёт. Мы говорим правду сразу.\n\n**Отказ второй: **документов нет, и восстановить их нечем. Суды выигрываются доказательствами. Если работы делались «по звонку», деньги ходили «как удобно», а переписка велась с личных номеров, мы честно назовём ваши шансы. Иногда они есть: в одном деле мы доказали объём работ через то, что заказчик сам сдал эти работы дальше, уже своему заказчику. Но такие ходы штучные. \n\n**Отказ третий: **экономика не сходится. Взыскивать 300 тысяч, потратив 250 и год жизни, так себе инвестиция. Здесь нам чаще всего и отказывать не приходится: мы показываем честную математику, и доверитель сам решает не идти в суд. Вместо него предложим претензию, переговоры или спокойное списание.\n\n**Отказ четвёртый:** между нами не возникло контакта. Так бывает, и это нормально. Для каждого доверителя есть свой специалист. Если мы не чувствуем друг друга в работе, честнее разойтись на старте, чем вести ваше дело без вовлечённости. Ваш спор заслуживает юриста, которому с вами по пути.\n\n**Отказ пятый: **вам нужна гарантия победы. Её не существует. Даже в самой однозначной ситуации, с подписанными актами и идеальными документами, никто честный не даст вам 100%. Кто обещает 100%, тот вам уже соврал. Если вы ищете именно гарантию, а не сильную позицию, мы не подойдём друг другу.\n\nОценку перспектив мы делаем до договора. **«Нет» вы слышите бесплатно. **Зато наше «да» значит одно: мы посчитали и верим в дело.\n\nОтчасти поэтому в нашей библиотеке 650+ выигранных дел. Мы просто не берём в работу будущие поражения. Ваши в том числе.\n\nСомневаетесь в своём споре? Пришлите документы в личку @grikevich. Посмотрим и скажем как есть: да, нет или «да, но не в суд».\n\nА вам хоть раз юрист говорил честное «нет»? Или все обещали победу и брали предоплату?",
    "views": 313,
    "forwards": 2,
    "has_media": false,
    "classification": {
      "signal": true,
      "score": 0.8,
      "category": "business",
      "summary": "Юрист объясняет, когда и почему отказывается от ведения дел, подчеркивая важность честного подхода.",
      "keywords": [
        "юрист",
        "отказ",
        "долг",
        "доказательства",
        "прозрачность"
      ]
    }
  }
]