[
  {
    "id": 893,
    "channel_id": "lch_legal",
    "date": "2026-07-11T07:08:52+00:00",
    "text": "__Обычно мы делимся подборками выставок, фестивалей и других культурных событий, но в этот раз собрали несколько идей для тех, кто предпочитает активный отдых. ____🔅__\n**\nФестиваль тенниса в Москве**\nВ эти выходные в парке «Ходынское поле» и на открытых кортах Дворца тенниса «Лужники» пройдет большой городской фестиваль. В программе — бесплатные занятия для всех желающих, мастер-классы от известных теннисистов, интерактивные зоны и призовые активности. Инвентарь предоставляют на месте, регистрация не требуется.\n[Подробнее](https://tennis.sport.mos.ru/).\n\n**Фестиваль силовых видов спорта «Прайд Спорт Фест»**\nНа одной площадке соберутся профессиональные спортсмены и любители силовых дисциплин. Гостей ждут соревнования по пауэрлифтингу, армрестлингу, гиревому спорту, силовые шоу, встречи с известными атлетами и активности для всей семьи. При желании можно не только посмотреть соревнования, но и принять участие в открытых турнирах.\n[Подробности. ](https://pride-united.ru/pride-sport-fest?erid=2SDnjboq9ZC)\n\n**SUP-прогулка «Сап миксер» в Серебряном Бору**\nЕсли хочется совместить физическую активность и отдых на природе, отличный вариант — прогулка на сапах по живописным маршрутам Серебряного Бора. Формат мероприятия предполагает не только катание, но и знакомство с новыми людьми. Подойдет даже тем, кто впервые встает на SUP-доску. [Детали](https://pb-club.ru/events/kollaby/sap-mikser-12-07-26?utm_source=kudago&erid=2SDnjcScKW9).",
    "views": 604,
    "forwards": 1,
    "has_media": false,
    "classification": {
      "signal": false,
      "score": 0.2,
      "category": "other",
      "summary": "Анонс культурных и спортивных мероприятий в Москве на выходные.",
      "keywords": [
        "фестиваль",
        "спорт",
        "теннис",
        "Суп-прогулка",
        "активный отдых"
      ]
    }
  }
]