[
  {
    "id": 1696,
    "channel_id": "library_lawyer",
    "date": "2026-06-24T07:01:01+00:00",
    "text": "**Хропанюк В.Н. \"Теория государства и права\" (2008)**\n\nУчебник базируется на принципах историзма, объективности и методах формальной и диалектической логики. В работе детально проанализированы статика и динамика отечественного законодательства, а также практика правового регулирования и её влияние на стабильность правового порядка в стране. Автор представляет собственные теоретические выводы, непосредственно связанные с процессами формирования и становления государственности в Российской Федерации. Издание сочетает фундаментальный научный подход с анализом современных правовых реалий, что делает его востребованным для изучения основ правоведения.\n\n#теориягосударстваиправа\n\n▫️ [Скачать](https://t.me/arhive_library_lawyer/2554)\n▫️ [Поиск литературы](https://t.me/library_lawyer/175)",
    "views": 776,
    "forwards": 14,
    "has_media": true,
    "classification": {
      "signal": false,
      "score": 0.1,
      "category": "other",
      "summary": "Описание учебника по теории государства и права без значимой новостной информации.",
      "keywords": [
        "теория государства",
        "право",
        "учебник",
        "анализ",
        "правовое регулирование"
      ]
    }
  }
]