[
  {
    "id": 8697,
    "channel_id": "povorotnapravo",
    "date": "2026-07-08T16:04:37+00:00",
    "text": "**Уволить за открытое резюме на сайте поиска работы нельзя\n**\nРоструд [напомнил](https://онлайнинспекция.рф/questions/view/249413), что наличие открытого резюме на сайте поиска работы не является основанием для увольнения сотрудника.\n\nПоводом для разъяснений стал вопрос работника, который открыл свое резюме со статусом «рассматриваю предложения», чтобы найти подработку. Работодатель пригрозил ему увольнением.\n\nЕсли сотрудник добросовестно исполняет свои обязанности по трудовому договору, то открытое резюме само по себе не может служить основанием для расторжения трудового договора.\n\nЕсли работодатель все же оказывает давление или угрожает увольнением по этой причине, работник вправе обратиться в трудовую инспекцию, прокуратуру или суд.\n\n@povorotnapravo",
    "views": 3009,
    "forwards": 32,
    "has_media": true,
    "classification": {
      "signal": true,
      "score": 0.8,
      "category": "business",
      "summary": "Роструд подтвердил, что открытое резюме на сайте поиска работы не может быть основанием для увольнения сотрудника.",
      "keywords": [
        "Роструд",
        "увольнение",
        "резюме",
        "трудовое право",
        "работа"
      ]
    }
  },
  {
    "id": 8696,
    "channel_id": "povorotnapravo",
    "date": "2026-07-08T06:56:17+00:00",
    "text": "**Утро среды. **[**Новости.**](https://s3.timeweb.com/b02450f6-4b380fc5-e73b-417d-a143-108a5c925b2b/web_page_preview/1bb1f0ef90.jpg)\n\n1. **Налоговая активнее спорит со старыми «налоговыми туристами»**\nИнспекции проверяют реальную связь бизнеса с льготным регионом и могут предлагать [доплатить налог](https://www.forbes.ru/finansy/564502-staryh-nalogovyh-turistov-stali-aktivno-lisat-l-got) до общей ставки даже компаниям, которые зарегистрированы там несколько лет.\n\n2. **Для продавцов на маркетплейсах предлагают поднять налоговую нагрузку**\nЭксперты оценили возможный недобор бюджета в 440-690 млрд руб. и предложили [ограничить льготы](https://pro.rbc.ru/demo/6a4d429c9a79472c45a62c63) по УСН, расширить НДС и обмен данными с ФНС по селлерам и ПВЗ.\n\n3. **Экспортерам хотят упростить вход в «Одно окно» через ЕСИА**\nПроект поправок позволит получать доступ к системе внешнеторговой деятельности [через ЕСИА](https://regulation.gov.ru/projects/169105/), включая работу с охраняемой законом тайной без обязательной УКЭП.\n\n4. **Суддеп меняет порядок официальной публикации актов**\nС 1 августа первым официальным опубликованием нормативных актов Суддепа может стать [размещение полного текста](https://regulation.gov.ru/projects/169136/) в приложении к журналу «Судья».\n\n5. **Третейские решения по договорам для ГОЗ могут не исполнить**\nСуд отказал в выдаче исполнительного листа, указав, что спор по договору для гособоронзаказа имеет публичный элемент и не может рассматриваться [без публичного контроля](https://kad.arbitr.ru/Card/5750c266-8735-4c72-bf08-1ef5fba03e2a).",
    "views": 3025,
    "forwards": 8,
    "has_media": true,
    "classification": {
      "signal": true,
      "score": 0.85,
      "category": "business",
      "summary": "Налоговые и нормативные изменения могут повлиять на бизнес и экспорт.",
      "keywords": [
        "налоговая политика",
        "экспорт",
        "нормативные акты",
        "бизнес",
        "государственный оборонный заказ"
      ]
    }
  }
]