[
  {
    "id": 3055,
    "channel_id": "lawsanctions",
    "date": "2026-07-20T11:59:55+00:00",
    "text": "**«Ваша карта бита» // Ринат Ахметшин не привлечёт Билла Браудера к ответственности в США**\n \n🇺🇸 Лоббист советского происхождения не согласился с [отказом](https://t.me/lawsanctions/1802) американских судов привлечь к ответственности за клевету Билла Браудера, «отца» закона об антироссийских санкциях имени Сергея Магнитского. Пошёл в апелляцию.\n\nСогласно фабуле дела, 🇬🇧 подданый Браудер дал интервью __CBS This Morning__ в Нью-Йорке. Во время интервью он рассказал об одной встрече, состоявшейся в Трамп-Тауэр в Нью-Йорке, __где присутствовал российский «шпион в Вашингтоне», округ Колумбия, по имени Ринат Ахметшин__. \n\nЦентральный вопрос дела – сконструировал ли Браудер этот комментарий так, чтобы **целенаправленно **привязать дело к округу Колумбия и таким образом избежать ответственности по его законодательству __Anti-SLAPP__? \n\nЕсли коротко, 🇺🇸 Вашингтон округ Колумбия – место сосредоточения федеральных политиков, где про них и лиц вокруг них можно говорить практически что угодно. \n\nЕсли – «да», то Браудер подлежит ответственности, если «нет», то и суда нет. Повышенное бремя доказывания такой «__целенаправленности__» лежит на заявителе. \n\nАпеллянт с ним не справился. Суд не признал Браудера подпадающим под юрисдикцию суда округа Колумбия. Постановление ⚖️ апелляционного суда 🇺🇸 от 17 июля [здесь](https://media.cadc.uscourts.gov/opinions/docs/2026/07/25-7008-2183743.pdf). \n\n#casestudy",
    "views": 833,
    "forwards": 5,
    "has_media": false,
    "classification": {
      "signal": true,
      "score": 0.8,
      "category": "politics",
      "summary": "Лоббист Ринат Ахметшин обжалует решение судов США по делу о клевете против Билла Браудера.",
      "keywords": [
        "Ахметшин",
        "Браудер",
        "клевета",
        "суд",
        "апелляция"
      ]
    }
  },
  {
    "id": 3054,
    "channel_id": "lawsanctions",
    "date": "2026-07-20T10:59:55+00:00",
    "text": "**Суд в США снял с паузы дело Нафтогаза против РФ о взыскании 4,2 млрд**\n\nВ деле о признании и приведении в исполнении решения ⚖️ трибунала при Постоянной палате Третейского суда в Гааге о взыскании с 🇷🇺 России 💲4,2 млрд Россия ходатайствовала о возврате иска 🇺🇦 заявителям и прекращении производства по делу в связи с отсутствием у ⚖️ суда 🇺🇸 компетенции на его рассмотрение.\n\nОбе стороны согласились приостановить рассмотрение до 1 апреля этого года в связи с обжалованием Россией третейского решения в ⚖️ государственных судах Нидерландов 🇳🇱\n\nПосле истечения срока Россия ходатайствовала о новой приостановке до момента пока ⚖️ Окружной суд Гааги 🇳🇱 не разрешит вопрос о действительности третейского решения, а ⚖️ Верховный суд США 🇺🇸 не выскажется о применении судами арбитражного исключения из закона __FSIA__ в 2 делах:\n\n1️⃣ __Russian Fed’n v. Stabil LLC, No__. 25-1093 и \n2️⃣ __Spain v. Blasket Investments LLC, No__. 24-1130\n\nНо 29 июня Верховный суд США [отказался](https://www.supremecourt.gov/orders/courtorders/062926zor_1bn2.pdf) принять к рассмотрению жалобы вместе с материалами в обоих делах. А 🇺🇦 заявители возражали против продления срока приостановления. \n\n⚖️ Федеральный суд округа Колумбия 🇺🇸 пошёл им на встречу и отклонил ходатайство России: __процессуальная экономия судебных ресурсов способствует скорейшему разрешению данного спора, а баланс потенциальных трудностей, связанных с продлением срока приостановления, склоняется в пользу заявителей. __\n\nОпределение 👨‍⚖️ судьи Джона Бейтса в деле __NJSC Naftogaz of Ukraine v. Russian Federation__ [здесь](https://ecf.dcd.uscourts.gov/cgi-bin/show_public_doc?2023cv1828-42). \n\n#международноеправо #суверенныйиммунитет",
    "views": 1132,
    "forwards": 9,
    "has_media": false,
    "classification": {
      "signal": true,
      "score": 0.85,
      "category": "business",
      "summary": "Суд в США продолжает дело Нафтогаза против России о взыскании 4,2 млрд долларов.",
      "keywords": [
        "Нафтогаз",
        "Россия",
        "взыскание",
        "суд",
        "международное право"
      ]
    }
  }
]