{
  "source": {
    "title": "Legaltech Hub обновил карту LegalTech-решений на основе генеративного ИИ",
    "url": "https://t.me/allthingslegal/1436",
    "published_at": "2026-07-02"
  },
  "platforms": {
    "telegram": {
      "content": "📌 Карта LegalTech-решений перевалила за тысячу сервисов\n\nLegaltech Hub обновил интерактивную карту LegalTech-решений на основе генеративного ИИ – база расширилась до 1196 решений в 19 категориях: документооборот, договорная работа, due diligence, комплаенс и другие.\n\nПочему это важно:\n– рынок инструментов вырос настолько, что почти под любую рутинную задачу уже есть готовый сервис;\n– карта разложена по категориям – можно быстро найти решение под конкретный процесс, а не собирать список вручную;\n– это не повод отказываться от своих наработок, а способ свериться с рынком перед тем, как заказывать доработку с нуля.\n\nЕсли планируете автоматизацию – сначала загляните в карту, возможно, велосипед уже изобретен.\n\nИсточник: All Things Legal → t.me/allthingslegal/1436"
    },
    "bitrix24": {
      "content": "[ИИ и право] Карта LegalTech-решений выросла до 1196 сервисов\n\nЧто произошло: Legaltech Hub обновил интерактивную карту LegalTech-решений на основе генеративного ИИ – база расширилась до 1196 решений в 19 категориях (документооборот, договорная работа, due diligence, комплаенс и другие).\n\nЧто это значит для нас: часть задач, которые сейчас закрываются вручную или через разрозненные сервисы, уже может иметь готовое решение на рынке – стоит свериться с картой, прежде чем заказывать доработку у своих разработчиков.\n\nЧто делаем: договорной отдел и IT смотрят карту по категориям «договорная работа» и «due diligence», короткий обзор находок принесем на летучку на следующей неделе."
    }
  }
}
